setup.py
lilypad/__init__.py
lilypad/lilypad.py
lilypad.egg-info/PKG-INFO
lilypad.egg-info/SOURCES.txt
lilypad.egg-info/dependency_links.txt
lilypad.egg-info/entry_points.txt
lilypad.egg-info/requires.txt
lilypad.egg-info/top_level.txt