Metadata-Version: 1.0
Name: lilypad
Version: 3.0.0
Summary: markdown + jinja, static site generator
Home-page: UNKNOWN
Author: Lily Seabreeze
Author-email: lillian.gardenia.seabreeze@gmail.com
License: UNKNOWN
Keywords: cli
Platform: UNKNOWN
